{
    "title": "Your title",
    "navigation": "horizontal",
    "menu-position": "right bottom",
    "width": 750,
    "height": 500,
    "theme": "default",
    "steps": [
        {
            "name": "Your first slide",
            "menu-icon": "/img/common/home.png",
            "spots": [
                {
                    "top": "27%",
                    "left": "30.26%",
                    "entrance": "fadeIn clockWise",
                    "type": "image",
                    "src": "https://dl.dropboxusercontent.com/u/25128734/kitten.jpg",
                    "width": 300
                }
            ]
        },
        {
            "name": "Your second slide",
            "spots": []
        }
    ]
}